odoo9_addon_partner_email_unique-9.0.1.0.0.99.dev8-nspkg.pth
odoo_addons/partner_email_unique/README.rst
odoo_addons/partner_email_unique/__init__.py
odoo_addons/partner_email_unique/__openerp__.py
odoo_addons/partner_email_unique/i18n/partner_email_unique.pot
odoo_addons/partner_email_unique/models/__init__.py
odoo_addons/partner_email_unique/models/res_partner.py
odoo_addons/partner_email_unique/readme/CONTRIBUTORS.rst
odoo_addons/partner_email_unique/readme/DESCRIPTION.rst
odoo_addons/partner_email_unique/readme/USAGE.rst
odoo_addons/partner_email_unique/static/description/icon.png
odoo_addons/partner_email_unique/static/description/index.html
odoo_addons/partner_email_unique/tests/__init__.py
odoo_addons/partner_email_unique/tests/test_res_partner_email.py
odoo9_addon_partner_email_unique-9.0.1.0.0.99.dev8.dist-info/METADATA
odoo9_addon_partner_email_unique-9.0.1.0.0.99.dev8.dist-info/WHEEL
odoo9_addon_partner_email_unique-9.0.1.0.0.99.dev8.dist-info/namespace_packages.txt
odoo9_addon_partner_email_unique-9.0.1.0.0.99.dev8.dist-info/top_level.txt
odoo9_addon_partner_email_unique-9.0.1.0.0.99.dev8.dist-info/RECORD
