Metadata-Version: 2.1
Name: odoo9-addon-partner-email-unique
Version: 9.0.1.0.0.99.dev8
Summary: Add an unique constraint to email field
Home-page: https://github.com/oca/partner-contact
Author: Coop IT Easy SCRL fs, Odoo Community Association (OCA)
Author-email: support@odoo-community.org
License: AGPL-3
Platform: UNKNOWN
Classifier: Programming Language :: Python
Classifier: Framework :: Odoo
Classifier: License :: OSI Approved :: GNU Affero General Public License v3
Requires-Python: ~=2.7
Requires-Dist: odoo (<9.1a,>=9.0a)
